Metadata-Version: 2.1
Name: colchian
Version: 0.2.1
Summary: Validate json/yaml documents using a Python dictionary defining keys and types.
Home-page: https://gitlab.com/jaapvandervelde/colchian
Author: BMT Commercial Australia Pty Ltd, Jaap van der Velde
Author-email: jaap.vandervelde@bmtglobal.com
License: MIT
Keywords: json,validator
Classifier: Development Status :: 4 - Beta
Classifier: Intended Audience :: Developers
Classifier: License :: OSI Approved :: MIT License
Classifier: Programming Language :: Python :: 3.7
Provides-Extra: dev
License-File: LICENSE
